catchem/__init__.py
catchem-0.0.0.dist-info/METADATA
catchem-0.0.0.dist-info/WHEEL
catchem-0.0.0.dist-info/RECORD
