Metadata-Version: 2.1
Name: catchem
Version: 0.0.0
Summary: Coming soon
Author: Kilian Schnelle
Author-email: kischnelle@icloud.com
Requires-Python: >=3.12,<4.0
Classifier: Programming Language :: Python :: 3
Classifier: Programming Language :: Python :: 3.12
Requires-Dist: typer (>=0.12.5,<0.13.0)
